.DS_Store
bitcoin_notifier/__init__.py
bitcoin_notifier/__main__.py
bitcoin_notifier/cli.py
bitcoin_notifier/utils.py
bitcoin_notifier-0.0.4.dist-info/LICENSE
bitcoin_notifier-0.0.4.dist-info/METADATA
bitcoin_notifier-0.0.4.dist-info/WHEEL
bitcoin_notifier-0.0.4.dist-info/entry_points.txt
bitcoin_notifier-0.0.4.dist-info/top_level.txt
bitcoin_notifier-0.0.4.dist-info/RECORD
