Metadata-Version: 2.1
Name: bitcoin-notifier
Version: 0.0.4
Summary: A Python package to get bitcoin updates and predictions
Home-page: https://github.com/anik-ghosh-au7/bitcoin_notifier
Author: Anik Ghosh
Author-email: tech.anikghosh@gmail.com
License: MIT
Platform: UNKNOWN
Classifier: License :: OSI Approved :: MIT License
Classifier: Programming Language :: Python :: 3
Classifier: Programming Language :: Python :: 3.7
Requires-Dist: requests
Requires-Dist: datetime
